LICENSE
MANIFEST.in
README.md
setup.py
dbtestpackage01/__init__.py
dbtestpackage01/github_api.py
dbtestpackage01.egg-info/PKG-INFO
dbtestpackage01.egg-info/SOURCES.txt
dbtestpackage01.egg-info/dependency_links.txt
dbtestpackage01.egg-info/not-zip-safe
dbtestpackage01.egg-info/requires.txt
dbtestpackage01.egg-info/top_level.txt
dbtestpackage01/spam/__init__.py
dbtestpackage01/spam/db.py
dbtestpackage01/spam/enviador_de_email.py
dbtestpackage01/spam/main.py
dbtestpackage01/test/__init__.py
dbtestpackage01/test/test_spam/__init__.py
dbtestpackage01/test/test_spam/conftest.py
dbtestpackage01/test/test_spam/test_enviador_de_emails.py
dbtestpackage01/test/test_spam/test_envio_para_banco_de_dados_do_usuario.py
dbtestpackage01/test/test_spam/test_github_api.py
dbtestpackage01/test/test_spam/test_usuario.py