Metadata-Version: 1.1
Name: dbtestpackage01
Version: 0.2
Summary: Just a package that I post on Pypi -- it's not  a big deal. 
Home-page: https://github.com/boybluepiano/dbtestpackage01
Author: Boybluepiano
Author-email: boybluepiano@gmail.com
License: UNKNOWN
Platform: UNKNOWN
Classifier: Development Status :: 2 - Pre-Alpha
Classifier: Environment :: Web Environment
Classifier: Intended Audience :: Developers
Classifier: License :: OSI Approved :: GNU Affero General Public License v3 or later (AGPLv3+)
Classifier: Operating System :: OS Independent
Classifier: Programming Language :: Python :: 3.8
Classifier: Framework :: Pytest
